[
  {
    "index": 0,
    "hash": "",
    "timestampUtcMs": "2026-05-13T13:00:06.755Z",
    "action": {
      "type": "CREATE_DOCUMENT",
      "input": {
        "meta": {},
        "name": "snapshot-report-model-provides-point-in-time-data-captures",
        "slug": "",
        "model": "bai/knowledge-note",
        "branch": "main",
        "signing": {
          "nonce": "",
          "publicKey": {},
          "signature": "5135bc30-5dc3-44f7-a604-f53b22b40793",
          "documentType": "bai/knowledge-note",
          "createdAtUtcIso": "2026-05-13T13:00:06.755Z"
        },
        "version": 0,
        "documentId": "5135bc30-5dc3-44f7-a604-f53b22b40793",
        "protocolVersions": {
          "base-reducer": 2
        }
      },
      "timestampUtcMs": "2026-05-13T13:00:06.755Z"
    }
  },
  {
    "index": 0,
    "hash": "DcU+Tt1Bwan0mFw+PHVWG1A4lg0=",
    "timestampUtcMs": "2026-05-13T13:00:44.000Z",
    "action": {
      "type": "SET_TITLE",
      "input": {
        "title": "snapshot-report model provides point-in-time data captures",
        "updatedAt": "2026-05-13T13:00:44.000Z"
      },
      "timestampUtcMs": "2026-05-13T13:00:44.000Z"
    }
  },
  {
    "index": 1,
    "hash": "",
    "timestampUtcMs": "2026-05-13T13:00:06.755Z",
    "action": {
      "type": "UPGRADE_DOCUMENT",
      "input": {
        "model": "bai/knowledge-note",
        "toVersion": 1,
        "documentId": "5135bc30-5dc3-44f7-a604-f53b22b40793",
        "fromVersion": 0,
        "initialState": {
          "auth": {},
          "local": {
            "lastViewedAt": null,
            "personalTags": []
          },
          "global": {
            "links": [],
            "model": null,
            "scope": null,
            "title": null,
            "editor": null,
            "inputs": [],
            "models": [],
            "status": "DRAFT",
            "topics": [],
            "content": null,
            "context": null,
            "modelId": null,
            "modules": [],
            "outputs": [],
            "version": null,
            "computes": null,
            "filePath": null,
            "noteType": null,
            "severity": null,
            "hooksUsed": [],
            "rootCause": null,
            "confidence": null,
            "consumedBy": [],
            "provenance": null,
            "sourceType": null,
            "targetType": null,
            "cardinality": null,
            "description": null,
            "alternatives": [],
            "consequences": [],
            "errorMessage": null,
            "relationType": null,
            "correctPattern": null,
            "decisionStatus": null,
            "dispatchTargets": [],
            "lifecycleEvents": []
          },
          "document": {
            "hash": {
              "encoding": "base64",
              "algorithm": "sha1"
            },
            "version": 0
          }
        }
      },
      "timestampUtcMs": "2026-05-13T13:00:06.755Z"
    }
  },
  {
    "index": 1,
    "hash": "5eTwrZroutnKjJkTNCM1fhwQuDg=",
    "timestampUtcMs": "2026-05-13T13:00:44.000Z",
    "action": {
      "type": "SET_DESCRIPTION",
      "input": {
        "updatedAt": "2026-05-13T13:00:44.000Z",
        "description": "18 operations \u2014 captures point-in-time snapshots of system state for reporting, auditing, and historical comparison"
      },
      "timestampUtcMs": "2026-05-13T13:00:44.000Z"
    }
  },
  {
    "index": 2,
    "hash": "",
    "timestampUtcMs": "2026-05-13T13:01:17.787Z",
    "action": {
      "type": "ADD_RELATIONSHIP",
      "input": {
        "sourceId": "5135bc30-5dc3-44f7-a604-f53b22b40793",
        "targetId": "96d2584d-af04-4557-8e79-b1f43312d8ca",
        "relationshipType": "RELATES_TO"
      },
      "timestampUtcMs": "2026-05-13T13:01:17.787Z"
    }
  },
  {
    "index": 2,
    "hash": "69PQO2cj2J4D/oTQEPd6EzWPNCg=",
    "timestampUtcMs": "2026-05-13T13:00:44.000Z",
    "action": {
      "type": "SET_NOTE_TYPE",
      "input": {
        "noteType": "ARCHITECTURE",
        "updatedAt": "2026-05-13T13:00:44.000Z"
      },
      "timestampUtcMs": "2026-05-13T13:00:44.000Z"
    }
  },
  {
    "index": 3,
    "hash": "",
    "timestampUtcMs": "2026-05-13T13:01:17.836Z",
    "action": {
      "type": "ADD_RELATIONSHIP",
      "input": {
        "sourceId": "5135bc30-5dc3-44f7-a604-f53b22b40793",
        "targetId": "46a28f33-95d0-4dab-83a7-dc2369e31e32",
        "relationshipType": "RELATES_TO"
      },
      "timestampUtcMs": "2026-05-13T13:01:17.836Z"
    }
  },
  {
    "index": 3,
    "hash": "TLhwzeDQUHXTSzf74oSQ7Vj82FM=",
    "timestampUtcMs": "2026-05-13T13:00:44.000Z",
    "action": {
      "type": "SET_CONTENT",
      "input": {
        "content": "# snapshot-report model provides point-in-time data captures\n\n`powerhouse/snapshot-report` (18 ops) creates frozen-in-time captures of system state. Useful for periodic reporting, compliance auditing, and historical trend analysis.\n\n## Position in Ecosystem\n\nReporting zone. May snapshot data from any other model for archival purposes.\n\n---\n\nTopics:\n- [[ecosystem map]]\n- [[object relations]]",
        "updatedAt": "2026-05-13T13:00:44.000Z"
      },
      "timestampUtcMs": "2026-05-13T13:00:44.000Z"
    }
  },
  {
    "index": 4,
    "hash": "",
    "timestampUtcMs": "2026-05-13T13:01:17.860Z",
    "action": {
      "type": "ADD_RELATIONSHIP",
      "input": {
        "sourceId": "5135bc30-5dc3-44f7-a604-f53b22b40793",
        "targetId": "a54a9f24-04ea-405c-89bd-b6c73d65fbe6",
        "relationshipType": "RELATES_TO"
      },
      "timestampUtcMs": "2026-05-13T13:01:17.860Z"
    }
  },
  {
    "index": 4,
    "hash": "rEbNBfRBC+GuufYsxL+nNw6emWs=",
    "timestampUtcMs": "2026-05-13T13:00:44.000Z",
    "action": {
      "type": "SET_PROVENANCE",
      "input": {
        "author": "knowledge-agent",
        "createdAt": "2026-04-03T13:43:03.000Z",
        "sourceOrigin": "IMPORT"
      },
      "timestampUtcMs": "2026-05-13T13:00:44.000Z"
    }
  },
  {
    "index": 5,
    "hash": "0/3gBSmf7FCh6wV/IvFnG3Q1M2I=",
    "timestampUtcMs": "2026-05-13T13:00:44.000Z",
    "action": {
      "type": "ADD_TOPIC",
      "input": {
        "id": "0e1ad568-a3ea-4d33-bbd2-995eb15c4471",
        "name": "snapshot-report",
        "topicDocumentId": null
      },
      "timestampUtcMs": "2026-05-13T13:00:44.000Z"
    }
  },
  {
    "index": 6,
    "hash": "mIxROJQds73beDQOP9Hgi+7kPLA=",
    "timestampUtcMs": "2026-05-13T13:00:44.000Z",
    "action": {
      "type": "ADD_TOPIC",
      "input": {
        "id": "5c68ade2-95a0-4e18-b3ab-fc63a7804ddd",
        "name": "reporting",
        "topicDocumentId": null
      },
      "timestampUtcMs": "2026-05-13T13:00:44.000Z"
    }
  }
]