[
  {
    "index": 0,
    "hash": "",
    "timestampUtcMs": "2026-05-13T12:59:42.163Z",
    "action": {
      "type": "CREATE_DOCUMENT",
      "input": {
        "meta": {},
        "name": "document-model-driven-architecture-rad",
        "slug": "",
        "model": "bai/knowledge-note",
        "branch": "main",
        "signing": {
          "nonce": "",
          "publicKey": {},
          "signature": "def5bfd1-15ed-48bf-8702-1eb93e02ea52",
          "documentType": "bai/knowledge-note",
          "createdAtUtcIso": "2026-05-13T12:59:42.163Z"
        },
        "version": 0,
        "documentId": "def5bfd1-15ed-48bf-8702-1eb93e02ea52",
        "protocolVersions": {
          "base-reducer": 2
        }
      },
      "timestampUtcMs": "2026-05-13T12:59:42.163Z"
    }
  },
  {
    "index": 0,
    "hash": "BJEXbh02NxG/omikhaKAZ8If23I=",
    "timestampUtcMs": "2026-05-13T13:00:32.000Z",
    "action": {
      "type": "SET_TITLE",
      "input": {
        "title": "Powerhouse uses document-model-driven architecture where document models are the core reusable unit enabling rapid application development",
        "updatedAt": "2026-05-13T13:00:32.000Z"
      },
      "timestampUtcMs": "2026-05-13T13:00:32.000Z"
    }
  },
  {
    "index": 1,
    "hash": "",
    "timestampUtcMs": "2026-05-13T12:59:42.163Z",
    "action": {
      "type": "UPGRADE_DOCUMENT",
      "input": {
        "model": "bai/knowledge-note",
        "toVersion": 1,
        "documentId": "def5bfd1-15ed-48bf-8702-1eb93e02ea52",
        "fromVersion": 0,
        "initialState": {
          "auth": {},
          "local": {
            "lastViewedAt": null,
            "personalTags": []
          },
          "global": {
            "links": [],
            "model": null,
            "scope": null,
            "title": null,
            "editor": null,
            "inputs": [],
            "models": [],
            "status": "DRAFT",
            "topics": [],
            "content": null,
            "context": null,
            "modelId": null,
            "modules": [],
            "outputs": [],
            "version": null,
            "computes": null,
            "filePath": null,
            "noteType": null,
            "severity": null,
            "hooksUsed": [],
            "rootCause": null,
            "confidence": null,
            "consumedBy": [],
            "provenance": null,
            "sourceType": null,
            "targetType": null,
            "cardinality": null,
            "description": null,
            "alternatives": [],
            "consequences": [],
            "errorMessage": null,
            "relationType": null,
            "correctPattern": null,
            "decisionStatus": null,
            "dispatchTargets": [],
            "lifecycleEvents": []
          },
          "document": {
            "hash": {
              "encoding": "base64",
              "algorithm": "sha1"
            },
            "version": 0
          }
        }
      },
      "timestampUtcMs": "2026-05-13T12:59:42.163Z"
    }
  },
  {
    "index": 1,
    "hash": "oGUk90VNJ1Y4ylCzFsc0ilA7r7U=",
    "timestampUtcMs": "2026-05-13T13:00:32.000Z",
    "action": {
      "type": "SET_DESCRIPTION",
      "input": {
        "updatedAt": "2026-05-13T13:00:32.000Z",
        "description": "Document models capture data, workflows, and operations as living entities; front-end devs can build UIs without managing backend state."
      },
      "timestampUtcMs": "2026-05-13T13:00:32.000Z"
    }
  },
  {
    "index": 2,
    "hash": "",
    "timestampUtcMs": "2026-05-13T13:01:01.474Z",
    "action": {
      "type": "ADD_RELATIONSHIP",
      "input": {
        "sourceId": "def5bfd1-15ed-48bf-8702-1eb93e02ea52",
        "targetId": "d2b638a0-513a-4d2b-b1e9-48f15e2188cb",
        "relationshipType": "RELATES_TO"
      },
      "timestampUtcMs": "2026-05-13T13:01:01.474Z"
    }
  },
  {
    "index": 2,
    "hash": "OgHCN8Qqg/nokQtU8yJ1w/u/KL8=",
    "timestampUtcMs": "2026-05-13T13:00:32.000Z",
    "action": {
      "type": "SET_NOTE_TYPE",
      "input": {
        "noteType": "ARCHITECTURE",
        "updatedAt": "2026-05-13T13:00:32.000Z"
      },
      "timestampUtcMs": "2026-05-13T13:00:32.000Z"
    }
  },
  {
    "index": 3,
    "hash": "",
    "timestampUtcMs": "2026-05-13T13:01:01.498Z",
    "action": {
      "type": "ADD_RELATIONSHIP",
      "input": {
        "sourceId": "def5bfd1-15ed-48bf-8702-1eb93e02ea52",
        "targetId": "85627fdf-da55-42eb-ae10-02c8f43516e8",
        "relationshipType": "RELATES_TO"
      },
      "timestampUtcMs": "2026-05-13T13:01:01.498Z"
    }
  },
  {
    "index": 3,
    "hash": "p/hpIhAUPHPkD0umj4JNv2AAJ9s=",
    "timestampUtcMs": "2026-05-13T13:00:32.000Z",
    "action": {
      "type": "SET_CONTENT",
      "input": {
        "content": "Powerhouse's architecture centers on document models as structured representations of data and workflows that evolve over time through operations. The three-layer architecture consists of: (1) Data Infrastructure Layer with the Reactor for storage/sync across local, cloud, and decentralized systems; (2) Host Application Layer with Connect, Switchboard, Fusion, Renown, and Academy as modular host apps gaining functionality through plugins; (3) Customization Layer for organization-specific plugins. Document models enable asynchronous collaboration (contributors work without linear processes), customizable processes (unique workflows per team), and event-driven updates. Front-end developers can 'plug into any document model and start building UI components without the hassle of managing backend or state management' -- the event-driven architecture handles it, like Redux without setup.",
        "updatedAt": "2026-05-13T13:00:32.000Z"
      },
      "timestampUtcMs": "2026-05-13T13:00:32.000Z"
    }
  },
  {
    "index": 4,
    "hash": "",
    "timestampUtcMs": "2026-05-13T13:01:01.519Z",
    "action": {
      "type": "ADD_RELATIONSHIP",
      "input": {
        "sourceId": "def5bfd1-15ed-48bf-8702-1eb93e02ea52",
        "targetId": "345dd7d5-2227-4257-bb2b-d152158c6986",
        "relationshipType": "RELATES_TO"
      },
      "timestampUtcMs": "2026-05-13T13:01:01.519Z"
    }
  },
  {
    "index": 4,
    "hash": "Y9CLwO+DD/AzFO/P8iZCua+GObg=",
    "timestampUtcMs": "2026-05-13T13:00:32.000Z",
    "action": {
      "type": "SET_PROVENANCE",
      "input": {
        "author": "knowledge-agent",
        "createdAt": "2026-04-02T12:00:00.000Z",
        "sourceOrigin": "DERIVED"
      },
      "timestampUtcMs": "2026-05-13T13:00:32.000Z"
    }
  },
  {
    "index": 5,
    "hash": "",
    "timestampUtcMs": "2026-05-13T13:01:01.539Z",
    "action": {
      "type": "ADD_RELATIONSHIP",
      "input": {
        "sourceId": "def5bfd1-15ed-48bf-8702-1eb93e02ea52",
        "targetId": "88b6d830-73ef-4792-a2e1-abd6950d89ab",
        "relationshipType": "RELATES_TO"
      },
      "timestampUtcMs": "2026-05-13T13:01:01.539Z"
    }
  },
  {
    "index": 5,
    "hash": "zs5qeDn22NlQwBFnebJnIxopXNw=",
    "timestampUtcMs": "2026-05-13T13:00:32.000Z",
    "action": {
      "type": "ADD_TOPIC",
      "input": {
        "id": "b78e76ab-4cb9-4520-8175-95123f12f967",
        "name": "document-model",
        "topicDocumentId": null
      },
      "timestampUtcMs": "2026-05-13T13:00:32.000Z"
    }
  },
  {
    "index": 6,
    "hash": "",
    "timestampUtcMs": "2026-05-13T13:01:01.558Z",
    "action": {
      "type": "ADD_RELATIONSHIP",
      "input": {
        "sourceId": "def5bfd1-15ed-48bf-8702-1eb93e02ea52",
        "targetId": "67ce34f9-bdbc-4ff4-96c9-66bbb2145772",
        "relationshipType": "BUILDS_ON"
      },
      "timestampUtcMs": "2026-05-13T13:01:01.558Z"
    }
  },
  {
    "index": 6,
    "hash": "E3N37ew2FE6+9IZWGWBiG/V4xkc=",
    "timestampUtcMs": "2026-05-13T13:00:32.000Z",
    "action": {
      "type": "ADD_TOPIC",
      "input": {
        "id": "4ec2853f-1f75-41dc-af8a-60fd7d48aa16",
        "name": "architecture",
        "topicDocumentId": null
      },
      "timestampUtcMs": "2026-05-13T13:00:32.000Z"
    }
  },
  {
    "index": 7,
    "hash": "bcYQq9bOuT8bEbfY3aBPlCuSpnI=",
    "timestampUtcMs": "2026-05-13T13:00:32.000Z",
    "action": {
      "type": "ADD_TOPIC",
      "input": {
        "id": "ba4729b7-3d2e-442b-bbb0-4eb0558da094",
        "name": "rapid-application-development",
        "topicDocumentId": null
      },
      "timestampUtcMs": "2026-05-13T13:00:32.000Z"
    }
  }
]