[
  {
    "index": 0,
    "hash": "",
    "timestampUtcMs": "2026-05-13T12:59:48.722Z",
    "action": {
      "type": "CREATE_DOCUMENT",
      "input": {
        "meta": {},
        "name": "invoice-model-generates-formal-payment-requests",
        "slug": "",
        "model": "bai/knowledge-note",
        "branch": "main",
        "signing": {
          "nonce": "",
          "publicKey": {},
          "signature": "f927cadf-4f92-40d7-9cb5-224ef7740f5c",
          "documentType": "bai/knowledge-note",
          "createdAtUtcIso": "2026-05-13T12:59:48.722Z"
        },
        "version": 0,
        "documentId": "f927cadf-4f92-40d7-9cb5-224ef7740f5c",
        "protocolVersions": {
          "base-reducer": 2
        }
      },
      "timestampUtcMs": "2026-05-13T12:59:48.722Z"
    }
  },
  {
    "index": 0,
    "hash": "RLeosl+L5+uJ/AlV4/ThVHBwUl4=",
    "timestampUtcMs": "2026-05-13T13:00:36.000Z",
    "action": {
      "type": "SET_TITLE",
      "input": {
        "title": "invoice model generates formal payment requests",
        "updatedAt": "2026-05-13T13:00:36.000Z"
      },
      "timestampUtcMs": "2026-05-13T13:00:36.000Z"
    }
  },
  {
    "index": 1,
    "hash": "",
    "timestampUtcMs": "2026-05-13T12:59:48.722Z",
    "action": {
      "type": "UPGRADE_DOCUMENT",
      "input": {
        "model": "bai/knowledge-note",
        "toVersion": 1,
        "documentId": "f927cadf-4f92-40d7-9cb5-224ef7740f5c",
        "fromVersion": 0,
        "initialState": {
          "auth": {},
          "local": {
            "lastViewedAt": null,
            "personalTags": []
          },
          "global": {
            "links": [],
            "model": null,
            "scope": null,
            "title": null,
            "editor": null,
            "inputs": [],
            "models": [],
            "status": "DRAFT",
            "topics": [],
            "content": null,
            "context": null,
            "modelId": null,
            "modules": [],
            "outputs": [],
            "version": null,
            "computes": null,
            "filePath": null,
            "noteType": null,
            "severity": null,
            "hooksUsed": [],
            "rootCause": null,
            "confidence": null,
            "consumedBy": [],
            "provenance": null,
            "sourceType": null,
            "targetType": null,
            "cardinality": null,
            "description": null,
            "alternatives": [],
            "consequences": [],
            "errorMessage": null,
            "relationType": null,
            "correctPattern": null,
            "decisionStatus": null,
            "dispatchTargets": [],
            "lifecycleEvents": []
          },
          "document": {
            "hash": {
              "encoding": "base64",
              "algorithm": "sha1"
            },
            "version": 0
          }
        }
      },
      "timestampUtcMs": "2026-05-13T12:59:48.722Z"
    }
  },
  {
    "index": 1,
    "hash": "HaIj3wbdjLaKQED98mAHhPL6D0c=",
    "timestampUtcMs": "2026-05-13T13:00:36.000Z",
    "action": {
      "type": "SET_DESCRIPTION",
      "input": {
        "updatedAt": "2026-05-13T13:00:36.000Z",
        "description": "31 operations (second largest) \u2014 creates formal invoices with line items, tax calculations, and payment status tracking"
      },
      "timestampUtcMs": "2026-05-13T13:00:36.000Z"
    }
  },
  {
    "index": 2,
    "hash": "",
    "timestampUtcMs": "2026-05-13T13:01:06.972Z",
    "action": {
      "type": "ADD_RELATIONSHIP",
      "input": {
        "sourceId": "f927cadf-4f92-40d7-9cb5-224ef7740f5c",
        "targetId": "84a25e1c-080c-401e-a2b8-cb2eaf2c32f5",
        "relationshipType": "RELATES_TO"
      },
      "timestampUtcMs": "2026-05-13T13:01:06.972Z"
    }
  },
  {
    "index": 2,
    "hash": "ejcAZf2oYaA9P0aHEQi+o/i/z+k=",
    "timestampUtcMs": "2026-05-13T13:00:36.000Z",
    "action": {
      "type": "SET_NOTE_TYPE",
      "input": {
        "noteType": "ARCHITECTURE",
        "updatedAt": "2026-05-13T13:00:36.000Z"
      },
      "timestampUtcMs": "2026-05-13T13:00:36.000Z"
    }
  },
  {
    "index": 3,
    "hash": "",
    "timestampUtcMs": "2026-05-13T13:01:06.993Z",
    "action": {
      "type": "ADD_RELATIONSHIP",
      "input": {
        "sourceId": "f927cadf-4f92-40d7-9cb5-224ef7740f5c",
        "targetId": "34b863c7-afa4-4b3d-958b-6937efca6f4f",
        "relationshipType": "RELATES_TO"
      },
      "timestampUtcMs": "2026-05-13T13:01:06.993Z"
    }
  },
  {
    "index": 3,
    "hash": "Ije3XfVMRFj/55SUmgUKInYZJxo=",
    "timestampUtcMs": "2026-05-13T13:00:36.000Z",
    "action": {
      "type": "SET_CONTENT",
      "input": {
        "content": "# invoice model generates formal payment requests\n\n`powerhouse/invoice` (31 ops) is the second-largest model by operation count. Generates formal invoices from subscription and billing data.\n\n## Cross-Model References\n\n- SubscriptionInstance \u2192 Invoice (subscription charges become invoice line items)\n- References [[payment-terms model defines payment conditions and schedules]] for due dates and terms\n- May reference [[billing-statement model captures periodic billing summaries]] as source data\n- Feeds into [[account-transactions model tracks financial transaction records]] when payments are recorded\n\n## Position in Ecosystem\n\nReporting zone. High operation count (31) suggests complex line item management, tax handling, and status workflow.\n\n---\n\nTopics:\n- [[ecosystem map]]\n- [[object relations]]",
        "updatedAt": "2026-05-13T13:00:36.000Z"
      },
      "timestampUtcMs": "2026-05-13T13:00:36.000Z"
    }
  },
  {
    "index": 4,
    "hash": "",
    "timestampUtcMs": "2026-05-13T13:01:07.012Z",
    "action": {
      "type": "ADD_RELATIONSHIP",
      "input": {
        "sourceId": "f927cadf-4f92-40d7-9cb5-224ef7740f5c",
        "targetId": "055a25fa-4a15-4dc8-bbd1-3a366c7040be",
        "relationshipType": "RELATES_TO"
      },
      "timestampUtcMs": "2026-05-13T13:01:07.012Z"
    }
  },
  {
    "index": 4,
    "hash": "vkk7sNCo7qp1L+Z4snM+a3INJP0=",
    "timestampUtcMs": "2026-05-13T13:00:36.000Z",
    "action": {
      "type": "SET_PROVENANCE",
      "input": {
        "author": "knowledge-agent",
        "createdAt": "2026-04-03T13:41:37.000Z",
        "sourceOrigin": "IMPORT"
      },
      "timestampUtcMs": "2026-05-13T13:00:36.000Z"
    }
  },
  {
    "index": 5,
    "hash": "",
    "timestampUtcMs": "2026-05-13T13:01:07.034Z",
    "action": {
      "type": "ADD_RELATIONSHIP",
      "input": {
        "sourceId": "f927cadf-4f92-40d7-9cb5-224ef7740f5c",
        "targetId": "46a28f33-95d0-4dab-83a7-dc2369e31e32",
        "relationshipType": "RELATES_TO"
      },
      "timestampUtcMs": "2026-05-13T13:01:07.034Z"
    }
  },
  {
    "index": 5,
    "hash": "D1mnRsp4LExIPEZ1OAeRgqi0M0g=",
    "timestampUtcMs": "2026-05-13T13:00:36.000Z",
    "action": {
      "type": "ADD_TOPIC",
      "input": {
        "id": "50dbcb3a-7664-48d5-8015-a62dd1e35baa",
        "name": "invoice",
        "topicDocumentId": null
      },
      "timestampUtcMs": "2026-05-13T13:00:36.000Z"
    }
  },
  {
    "index": 6,
    "hash": "",
    "timestampUtcMs": "2026-05-13T13:01:07.057Z",
    "action": {
      "type": "ADD_RELATIONSHIP",
      "input": {
        "sourceId": "f927cadf-4f92-40d7-9cb5-224ef7740f5c",
        "targetId": "647e3ae9-3176-4df3-8e82-b6c913f4823e",
        "relationshipType": "RELATES_TO"
      },
      "timestampUtcMs": "2026-05-13T13:01:07.057Z"
    }
  },
  {
    "index": 6,
    "hash": "QBR6HcS+9T3WCbJQIDu+PkWn4hY=",
    "timestampUtcMs": "2026-05-13T13:00:36.000Z",
    "action": {
      "type": "ADD_TOPIC",
      "input": {
        "id": "1ae47ad3-529f-402c-8210-9ead5a0adb11",
        "name": "reporting",
        "topicDocumentId": null
      },
      "timestampUtcMs": "2026-05-13T13:00:36.000Z"
    }
  }
]